[
  {
    "timestamp": "2025-09-13 16:39:34",
    "scan_id": "20250913_162520",
    "ticker": "ADANIPOWER",
    "quarterly_results": {
      "Sales+": {
        "Jun 2022": "13,723",
        "Sep 2022": "7,044",
        "Dec 2022": "7,764",
        "Mar 2023": "10,242",
        "Jun 2023": "11,006",
        "Sep 2023": "12,991",
        "Dec 2023": "12,991",
        "Mar 2024": "13,364",
        "Jun 2024": "14,956",
        "Sep 2024": "13,339",
        "Dec 2024": "13,671",
        "Mar 2025": "14,237",
        "Jun 2025": "14,109"
      },
      "Expenses+": {
        "Jun 2022": "8,003",
        "Sep 2022": "6,096",
        "Dec 2022": "6,295",
        "Mar 2023": "8,335",
        "Jun 2023": "7,491",
        "Sep 2023": "7,819",
        "Dec 2023": "8,346",
        "Mar 2024": "8,514",
        "Jun 2024": "8,761",
        "Sep 2024": "8,063",
        "Dec 2024": "8,648",
        "Mar 2025": "9,425",
        "Jun 2025": "8,424"
      },
      "Operating Profit": {
        "Jun 2022": "5,720",
        "Sep 2022": "948",
        "Dec 2022": "1,470",
        "Mar 2023": "1,907",
        "Jun 2023": "3,514",
        "Sep 2023": "5,171",
        "Dec 2023": "4,645",
        "Mar 2024": "4,850",
        "Jun 2024": "6,194",
        "Sep 2024": "5,276",
        "Dec 2024": "5,023",
        "Mar 2025": "4,813",
        "Jun 2025": "5,685"
      },
      "OPM %": {
        "Jun 2022": "42%",
        "Sep 2022": "13%",
        "Dec 2022": "19%",
        "Mar 2023": "19%",
        "Jun 2023": "32%",
        "Sep 2023": "40%",
        "Dec 2023": "36%",
        "Mar 2024": "36%",
        "Jun 2024": "41%",
        "Sep 2024": "40%",
        "Dec 2024": "37%",
        "Mar 2025": "34%",
        "Jun 2025": "40%"
      },
      "Other Income+": {
        "Jun 2022": "1,786",
        "Sep 2022": "1,402",
        "Dec 2022": "526",
        "Mar 2023": "553",
        "Jun 2023": "7,103",
        "Sep 2023": "1,945",
        "Dec 2023": "364",
        "Mar 2024": "518",
        "Jun 2024": "518",
        "Sep 2024": "724",
        "Dec 2024": "1,162",
        "Mar 2025": "298",
        "Jun 2025": "465"
      },
      "Interest": {
        "Jun 2022": "823",
        "Sep 2022": "818",
        "Dec 2022": "946",
        "Mar 2023": "746",
        "Jun 2023": "883",
        "Sep 2023": "888",
        "Dec 2023": "797",
        "Mar 2024": "820",
        "Jun 2024": "811",
        "Sep 2024": "807",
        "Dec 2024": "957",
        "Mar 2025": "765",
        "Jun 2025": "857"
      },
      "Depreciation": {
        "Jun 2022": "816",
        "Sep 2022": "833",
        "Dec 2022": "838",
        "Mar 2023": "817",
        "Jun 2023": "935",
        "Sep 2023": "1,004",
        "Dec 2023": "1,002",
        "Mar 2024": "990",
        "Jun 2024": "996",
        "Sep 2024": "1,059",
        "Dec 2024": "1,170",
        "Mar 2025": "1,085",
        "Jun 2025": "1,089"
      },
      "Profit before tax": {
        "Jun 2022": "5,866",
        "Sep 2022": "699",
        "Dec 2022": "212",
        "Mar 2023": "898",
        "Jun 2023": "8,800",
        "Sep 2023": "5,224",
        "Dec 2023": "3,210",
        "Mar 2024": "3,558",
        "Jun 2024": "4,906",
        "Sep 2024": "4,134",
        "Dec 2024": "4,059",
        "Mar 2025": "3,261",
        "Jun 2025": "4,204"
      },
      "Tax %": {
        "Jun 2022": "19%",
        "Sep 2022": "0%",
        "Dec 2022": "96%",
        "Mar 2023": "-484%",
        "Jun 2023": "0%",
        "Sep 2023": "-26%",
        "Dec 2023": "15%",
        "Mar 2024": "23%",
        "Jun 2024": "20%",
        "Sep 2024": "20%",
        "Dec 2024": "28%",
        "Mar 2025": "20%",
        "Jun 2025": "21%"
      },
      "Net Profit+": {
        "Jun 2022": "4,780",
        "Sep 2022": "696",
        "Dec 2022": "9",
        "Mar 2023": "5,242",
        "Jun 2023": "8,759",
        "Sep 2023": "6,594",
        "Dec 2023": "2,738",
        "Mar 2024": "2,737",
        "Jun 2024": "3,913",
        "Sep 2024": "3,298",
        "Dec 2024": "2,940",
        "Mar 2025": "2,599",
        "Jun 2025": "3,305"
      },
      "EPS in Rs": {
        "Jun 2022": "12.39",
        "Sep 2022": "1.80",
        "Dec 2022": "0.02",
        "Mar 2023": "13.59",
        "Jun 2023": "22.71",
        "Sep 2023": "17.10",
        "Dec 2023": "7.10",
        "Mar 2024": "7.10",
        "Jun 2024": "10.14",
        "Sep 2024": "8.64",
        "Dec 2024": "7.93",
        "Mar 2025": "6.84",
        "Jun 2025": "8.78"
      },
      "Raw PDF": {
        "Jun 2022": "",
        "Sep 2022": "",
        "Dec 2022": "",
        "Mar 2023": "",
        "Jun 2023": "",
        "Sep 2023": "",
        "Dec 2023": "",
        "Mar 2024": "",
        "Jun 2024": "",
        "Sep 2024": "",
        "Dec 2024": "",
        "Mar 2025": "",
        "Jun 2025": ""
      }
    },
    "balance_sheet": {
      "Equity Capital": {
        "Mar 2014": "2,872",
        "Mar 2015": "2,872",
        "Mar 2016": "3,334",
        "Mar 2017": "3,857",
        "Mar 2018": "3,857",
        "Mar 2019": "3,857",
        "Mar 2020": "3,857",
        "Mar 2021": "3,857",
        "Mar 2022": "3,857",
        "Mar 2023": "3,857",
        "Mar 2024": "3,857",
        "Mar 2025": "3,857"
      },
      "Reserves": {
        "Mar 2014": "3,671",
        "Mar 2015": "2,853",
        "Mar 2016": "4,134",
        "Mar 2017": "-857",
        "Mar 2018": "-2,968",
        "Mar 2019": "3,855",
        "Mar 2020": "2,624",
        "Mar 2021": "9,256",
        "Mar 2022": "14,600",
        "Mar 2023": "26,019",
        "Mar 2024": "39,042",
        "Mar 2025": "52,490"
      },
      "Borrowings+": {
        "Mar 2014": "44,150",
        "Mar 2015": "44,742",
        "Mar 2016": "52,729",
        "Mar 2017": "52,484",
        "Mar 2018": "52,835",
        "Mar 2019": "46,980",
        "Mar 2020": "55,199",
        "Mar 2021": "52,519",
        "Mar 2022": "49,145",
        "Mar 2023": "42,350",
        "Mar 2024": "34,862",
        "Mar 2025": "39,495"
      },
      "Other Liabilities+": {
        "Mar 2014": "8,045",
        "Mar 2015": "8,008",
        "Mar 2016": "15,597",
        "Mar 2017": "16,027",
        "Mar 2018": "15,804",
        "Mar 2019": "13,293",
        "Mar 2020": "13,346",
        "Mar 2021": "13,175",
        "Mar 2022": "14,379",
        "Mar 2023": "13,596",
        "Mar 2024": "14,248",
        "Mar 2025": "17,076"
      },
      "Total Liabilities": {
        "Mar 2014": "58,739",
        "Mar 2015": "58,474",
        "Mar 2016": "75,794",
        "Mar 2017": "71,511",
        "Mar 2018": "69,528",
        "Mar 2019": "67,985",
        "Mar 2020": "75,025",
        "Mar 2021": "78,806",
        "Mar 2022": "81,981",
        "Mar 2023": "85,821",
        "Mar 2024": "92,009",
        "Mar 2025": "112,918"
      },
      "Fixed Assets+": {
        "Mar 2014": "46,365",
        "Mar 2015": "45,080",
        "Mar 2016": "56,941",
        "Mar 2017": "54,391",
        "Mar 2018": "52,137",
        "Mar 2019": "50,419",
        "Mar 2020": "55,846",
        "Mar 2021": "52,851",
        "Mar 2022": "53,274",
        "Mar 2023": "51,451",
        "Mar 2024": "63,016",
        "Mar 2025": "69,297"
      },
      "CWIP": {
        "Mar 2014": "3,660",
        "Mar 2015": "191",
        "Mar 2016": "88",
        "Mar 2017": "125",
        "Mar 2018": "120",
        "Mar 2019": "350",
        "Mar 2020": "2,347",
        "Mar 2021": "6,439",
        "Mar 2022": "10,270",
        "Mar 2023": "12,880",
        "Mar 2024": "925",
        "Mar 2025": "12,104"
      },
      "Investments": {
        "Mar 2014": "115",
        "Mar 2015": "357",
        "Mar 2016": "0",
        "Mar 2017": "164",
        "Mar 2018": "0",
        "Mar 2019": "3",
        "Mar 2020": "3",
        "Mar 2021": "20",
        "Mar 2022": "183",
        "Mar 2023": "654",
        "Mar 2024": "374",
        "Mar 2025": "1,097"
      },
      "Other Assets+": {
        "Mar 2014": "8,599",
        "Mar 2015": "12,846",
        "Mar 2016": "18,765",
        "Mar 2017": "16,831",
        "Mar 2018": "17,271",
        "Mar 2019": "17,213",
        "Mar 2020": "16,830",
        "Mar 2021": "19,495",
        "Mar 2022": "18,254",
        "Mar 2023": "20,836",
        "Mar 2024": "27,694",
        "Mar 2025": "30,418"
      },
      "Total Assets": {
        "Mar 2014": "58,739",
        "Mar 2015": "58,474",
        "Mar 2016": "75,794",
        "Mar 2017": "71,511",
        "Mar 2018": "69,528",
        "Mar 2019": "67,985",
        "Mar 2020": "75,025",
        "Mar 2021": "78,806",
        "Mar 2022": "81,981",
        "Mar 2023": "85,821",
        "Mar 2024": "92,009",
        "Mar 2025": "112,918"
      }
    },
    "cash_flow": {
      "Cash from Operating Activity+": {
        "Mar 2014": "3,238",
        "Mar 2015": "5,824",
        "Mar 2016": "5,257",
        "Mar 2017": "4,725",
        "Mar 2018": "5,101",
        "Mar 2019": "5,610",
        "Mar 2020": "5,598",
        "Mar 2021": "7,014",
        "Mar 2022": "10,233",
        "Mar 2023": "8,431",
        "Mar 2024": "14,170",
        "Mar 2025": "21,501"
      },
      "Cash from Investing Activity+": {
        "Mar 2014": "-4,700",
        "Mar 2015": "-4,737",
        "Mar 2016": "-2,692",
        "Mar 2017": "-1,212",
        "Mar 2018": "-520",
        "Mar 2019": "-984",
        "Mar 2020": "-2,304",
        "Mar 2021": "-2,188",
        "Mar 2022": "774",
        "Mar 2023": "1,545",
        "Mar 2024": "3,481",
        "Mar 2025": "-17,142"
      },
      "Cash from Financing Activity+": {
        "Mar 2014": "1,631",
        "Mar 2015": "-1,144",
        "Mar 2016": "-2,713",
        "Mar 2017": "-3,539",
        "Mar 2018": "-4,600",
        "Mar 2019": "-4,663",
        "Mar 2020": "-2,377",
        "Mar 2021": "-5,655",
        "Mar 2022": "-10,338",
        "Mar 2023": "-10,408",
        "Mar 2024": "-16,864",
        "Mar 2025": "-5,175"
      },
      "Net Cash Flow": {
        "Mar 2014": "169",
        "Mar 2015": "-58",
        "Mar 2016": "-148",
        "Mar 2017": "-26",
        "Mar 2018": "-19",
        "Mar 2019": "-37",
        "Mar 2020": "917",
        "Mar 2021": "-828",
        "Mar 2022": "669",
        "Mar 2023": "-433",
        "Mar 2024": "787",
        "Mar 2025": "-816"
      }
    },
    "ratios": {
      "Debtor Days": {
        "Mar 2014": "37",
        "Mar 2015": "68",
        "Mar 2016": "179",
        "Mar 2017": "124",
        "Mar 2018": "109",
        "Mar 2019": "131",
        "Mar 2020": "115",
        "Mar 2021": "165",
        "Mar 2022": "126",
        "Mar 2023": "109",
        "Mar 2024": "85",
        "Mar 2025": "85"
      },
      "Inventory Days": {
        "Mar 2014": "",
        "Mar 2015": "",
        "Mar 2016": "",
        "Mar 2017": "",
        "Mar 2018": "",
        "Mar 2019": "",
        "Mar 2020": "",
        "Mar 2021": "",
        "Mar 2022": "",
        "Mar 2023": "",
        "Mar 2024": "",
        "Mar 2025": ""
      },
      "Days Payable": {
        "Mar 2014": "",
        "Mar 2015": "",
        "Mar 2016": "",
        "Mar 2017": "",
        "Mar 2018": "",
        "Mar 2019": "",
        "Mar 2020": "",
        "Mar 2021": "",
        "Mar 2022": "",
        "Mar 2023": "",
        "Mar 2024": "",
        "Mar 2025": ""
      },
      "Cash Conversion Cycle": {
        "Mar 2014": "37",
        "Mar 2015": "68",
        "Mar 2016": "179",
        "Mar 2017": "124",
        "Mar 2018": "109",
        "Mar 2019": "131",
        "Mar 2020": "115",
        "Mar 2021": "165",
        "Mar 2022": "126",
        "Mar 2023": "109",
        "Mar 2024": "85",
        "Mar 2025": "85"
      },
      "Working Capital Days": {
        "Mar 2014": "-289",
        "Mar 2015": "-161",
        "Mar 2016": "-154",
        "Mar 2017": "-208",
        "Mar 2018": "-269",
        "Mar 2019": "-90",
        "Mar 2020": "-77",
        "Mar 2021": "-38",
        "Mar 2022": "-46",
        "Mar 2023": "-6",
        "Mar 2024": "16",
        "Mar 2025": "18"
      },
      "ROCE %": {
        "Mar 2014": "6%",
        "Mar 2015": "7%",
        "Mar 2016": "11%",
        "Mar 2017": "6%",
        "Mar 2018": "6%",
        "Mar 2019": "9%",
        "Mar 2020": "7%",
        "Mar 2021": "12%",
        "Mar 2022": "16%",
        "Mar 2023": "16%",
        "Mar 2024": "32%",
        "Mar 2025": "23%"
      }
    },
    "shareholding_pattern": {
      "Sep 2022": {
        "Promoters+": "74.97",
        "FIIs+": "13.23",
        "DIIs+": "0.00",
        "Public+": "11.80"
      },
      "Dec 2022": {
        "Promoters+": "74.97",
        "FIIs+": "12.88",
        "DIIs+": "0.00",
        "Public+": "12.15"
      },
      "Mar 2023": {
        "Promoters+": "74.97",
        "FIIs+": "11.70",
        "DIIs+": "0.01",
        "Public+": "13.32"
      },
      "Jun 2023": {
        "Promoters+": "74.97",
        "FIIs+": "11.95",
        "DIIs+": "0.04",
        "Public+": "13.04"
      },
      "Sep 2023": {
        "Promoters+": "70.02",
        "FIIs+": "17.51",
        "DIIs+": "0.76",
        "Public+": "11.72"
      },
      "Dec 2023": {
        "Promoters+": "71.75",
        "FIIs+": "15.86",
        "DIIs+": "1.18",
        "Public+": "11.20"
      },
      "Mar 2024": {
        "Promoters+": "71.75",
        "FIIs+": "15.91",
        "DIIs+": "1.41",
        "Public+": "10.93"
      },
      "Jun 2024": {
        "Promoters+": "72.71",
        "FIIs+": "14.73",
        "DIIs+": "1.42",
        "Public+": "11.14"
      },
      "Sep 2024": {
        "Promoters+": "74.96",
        "FIIs+": "12.66",
        "DIIs+": "1.52",
        "Public+": "10.84"
      },
      "Dec 2024": {
        "Promoters+": "74.96",
        "FIIs+": "12.34",
        "DIIs+": "1.60",
        "Public+": "11.09"
      },
      "Mar 2025": {
        "Promoters+": "74.96",
        "FIIs+": "12.36",
        "DIIs+": "1.64",
        "Public+": "11.03"
      },
      "Jun 2025": {
        "Promoters+": "74.96",
        "FIIs+": "12.46",
        "DIIs+": "1.76",
        "Public+": "10.82"
      },
      "Mar 2017": {
        "Promoters+": "68.08",
        "FIIs+": "22.12",
        "DIIs+": "2.67",
        "Public+": "7.12"
      },
      "Mar 2018": {
        "Promoters+": "73.07",
        "FIIs+": "11.28",
        "DIIs+": "9.14",
        "Public+": "6.51"
      },
      "Mar 2019": {
        "Promoters+": "74.97",
        "FIIs+": "10.02",
        "DIIs+": "10.11",
        "Public+": "4.90"
      },
      "Mar 2020": {
        "Promoters+": "74.97",
        "FIIs+": "12.38",
        "DIIs+": "8.29",
        "Public+": "4.35"
      },
      "Mar 2021": {
        "Promoters+": "74.97",
        "FIIs+": "11.52",
        "DIIs+": "7.08",
        "Public+": "6.43"
      },
      "Mar 2022": {
        "Promoters+": "74.97",
        "FIIs+": "11.31",
        "DIIs+": "5.56",
        "Public+": "8.15"
      }
    }
  },
  {
    "timestamp": "2025-09-18 14:22:21",
    "scan_id": "20250918_135206",
    "ticker": "ADANIPOWER",
    "quarterly_results": {
      "Sales+": {
        "Jun 2022": "13,723",
        "Sep 2022": "7,044",
        "Dec 2022": "7,764",
        "Mar 2023": "10,242",
        "Jun 2023": "11,006",
        "Sep 2023": "12,991",
        "Dec 2023": "12,991",
        "Mar 2024": "13,364",
        "Jun 2024": "14,956",
        "Sep 2024": "13,339",
        "Dec 2024": "13,671",
        "Mar 2025": "14,237",
        "Jun 2025": "14,109"
      },
      "Expenses+": {
        "Jun 2022": "8,003",
        "Sep 2022": "6,096",
        "Dec 2022": "6,295",
        "Mar 2023": "8,335",
        "Jun 2023": "7,491",
        "Sep 2023": "7,819",
        "Dec 2023": "8,346",
        "Mar 2024": "8,514",
        "Jun 2024": "8,761",
        "Sep 2024": "8,063",
        "Dec 2024": "8,648",
        "Mar 2025": "9,425",
        "Jun 2025": "8,424"
      },
      "Operating Profit": {
        "Jun 2022": "5,720",
        "Sep 2022": "948",
        "Dec 2022": "1,470",
        "Mar 2023": "1,907",
        "Jun 2023": "3,514",
        "Sep 2023": "5,171",
        "Dec 2023": "4,645",
        "Mar 2024": "4,850",
        "Jun 2024": "6,194",
        "Sep 2024": "5,276",
        "Dec 2024": "5,023",
        "Mar 2025": "4,813",
        "Jun 2025": "5,685"
      },
      "OPM %": {
        "Jun 2022": "42%",
        "Sep 2022": "13%",
        "Dec 2022": "19%",
        "Mar 2023": "19%",
        "Jun 2023": "32%",
        "Sep 2023": "40%",
        "Dec 2023": "36%",
        "Mar 2024": "36%",
        "Jun 2024": "41%",
        "Sep 2024": "40%",
        "Dec 2024": "37%",
        "Mar 2025": "34%",
        "Jun 2025": "40%"
      },
      "Other Income+": {
        "Jun 2022": "1,786",
        "Sep 2022": "1,402",
        "Dec 2022": "526",
        "Mar 2023": "553",
        "Jun 2023": "7,103",
        "Sep 2023": "1,945",
        "Dec 2023": "364",
        "Mar 2024": "518",
        "Jun 2024": "518",
        "Sep 2024": "724",
        "Dec 2024": "1,162",
        "Mar 2025": "298",
        "Jun 2025": "465"
      },
      "Interest": {
        "Jun 2022": "823",
        "Sep 2022": "818",
        "Dec 2022": "946",
        "Mar 2023": "746",
        "Jun 2023": "883",
        "Sep 2023": "888",
        "Dec 2023": "797",
        "Mar 2024": "820",
        "Jun 2024": "811",
        "Sep 2024": "807",
        "Dec 2024": "957",
        "Mar 2025": "765",
        "Jun 2025": "857"
      },
      "Depreciation": {
        "Jun 2022": "816",
        "Sep 2022": "833",
        "Dec 2022": "838",
        "Mar 2023": "817",
        "Jun 2023": "935",
        "Sep 2023": "1,004",
        "Dec 2023": "1,002",
        "Mar 2024": "990",
        "Jun 2024": "996",
        "Sep 2024": "1,059",
        "Dec 2024": "1,170",
        "Mar 2025": "1,085",
        "Jun 2025": "1,089"
      },
      "Profit before tax": {
        "Jun 2022": "5,866",
        "Sep 2022": "699",
        "Dec 2022": "212",
        "Mar 2023": "898",
        "Jun 2023": "8,800",
        "Sep 2023": "5,224",
        "Dec 2023": "3,210",
        "Mar 2024": "3,558",
        "Jun 2024": "4,906",
        "Sep 2024": "4,134",
        "Dec 2024": "4,059",
        "Mar 2025": "3,261",
        "Jun 2025": "4,204"
      },
      "Tax %": {
        "Jun 2022": "19%",
        "Sep 2022": "0%",
        "Dec 2022": "96%",
        "Mar 2023": "-484%",
        "Jun 2023": "0%",
        "Sep 2023": "-26%",
        "Dec 2023": "15%",
        "Mar 2024": "23%",
        "Jun 2024": "20%",
        "Sep 2024": "20%",
        "Dec 2024": "28%",
        "Mar 2025": "20%",
        "Jun 2025": "21%"
      },
      "Net Profit+": {
        "Jun 2022": "4,780",
        "Sep 2022": "696",
        "Dec 2022": "9",
        "Mar 2023": "5,242",
        "Jun 2023": "8,759",
        "Sep 2023": "6,594",
        "Dec 2023": "2,738",
        "Mar 2024": "2,737",
        "Jun 2024": "3,913",
        "Sep 2024": "3,298",
        "Dec 2024": "2,940",
        "Mar 2025": "2,599",
        "Jun 2025": "3,305"
      },
      "EPS in Rs": {
        "Jun 2022": "12.39",
        "Sep 2022": "1.80",
        "Dec 2022": "0.02",
        "Mar 2023": "13.59",
        "Jun 2023": "22.71",
        "Sep 2023": "17.10",
        "Dec 2023": "7.10",
        "Mar 2024": "7.10",
        "Jun 2024": "10.14",
        "Sep 2024": "8.64",
        "Dec 2024": "7.93",
        "Mar 2025": "6.84",
        "Jun 2025": "8.78"
      },
      "Raw PDF": {
        "Jun 2022": "",
        "Sep 2022": "",
        "Dec 2022": "",
        "Mar 2023": "",
        "Jun 2023": "",
        "Sep 2023": "",
        "Dec 2023": "",
        "Mar 2024": "",
        "Jun 2024": "",
        "Sep 2024": "",
        "Dec 2024": "",
        "Mar 2025": "",
        "Jun 2025": ""
      }
    },
    "balance_sheet": {
      "Equity Capital": {
        "Mar 2014": "2,872",
        "Mar 2015": "2,872",
        "Mar 2016": "3,334",
        "Mar 2017": "3,857",
        "Mar 2018": "3,857",
        "Mar 2019": "3,857",
        "Mar 2020": "3,857",
        "Mar 2021": "3,857",
        "Mar 2022": "3,857",
        "Mar 2023": "3,857",
        "Mar 2024": "3,857",
        "Mar 2025": "3,857"
      },
      "Reserves": {
        "Mar 2014": "3,671",
        "Mar 2015": "2,853",
        "Mar 2016": "4,134",
        "Mar 2017": "-857",
        "Mar 2018": "-2,968",
        "Mar 2019": "3,855",
        "Mar 2020": "2,624",
        "Mar 2021": "9,256",
        "Mar 2022": "14,600",
        "Mar 2023": "26,019",
        "Mar 2024": "39,042",
        "Mar 2025": "52,490"
      },
      "Borrowings+": {
        "Mar 2014": "44,150",
        "Mar 2015": "44,742",
        "Mar 2016": "52,729",
        "Mar 2017": "52,484",
        "Mar 2018": "52,835",
        "Mar 2019": "46,980",
        "Mar 2020": "55,199",
        "Mar 2021": "52,519",
        "Mar 2022": "49,145",
        "Mar 2023": "42,350",
        "Mar 2024": "34,862",
        "Mar 2025": "39,495"
      },
      "Other Liabilities+": {
        "Mar 2014": "8,045",
        "Mar 2015": "8,008",
        "Mar 2016": "15,597",
        "Mar 2017": "16,027",
        "Mar 2018": "15,804",
        "Mar 2019": "13,293",
        "Mar 2020": "13,346",
        "Mar 2021": "13,175",
        "Mar 2022": "14,379",
        "Mar 2023": "13,596",
        "Mar 2024": "14,248",
        "Mar 2025": "17,076"
      },
      "Total Liabilities": {
        "Mar 2014": "58,739",
        "Mar 2015": "58,474",
        "Mar 2016": "75,794",
        "Mar 2017": "71,511",
        "Mar 2018": "69,528",
        "Mar 2019": "67,985",
        "Mar 2020": "75,025",
        "Mar 2021": "78,806",
        "Mar 2022": "81,981",
        "Mar 2023": "85,821",
        "Mar 2024": "92,009",
        "Mar 2025": "112,918"
      },
      "Fixed Assets+": {
        "Mar 2014": "46,365",
        "Mar 2015": "45,080",
        "Mar 2016": "56,941",
        "Mar 2017": "54,391",
        "Mar 2018": "52,137",
        "Mar 2019": "50,419",
        "Mar 2020": "55,846",
        "Mar 2021": "52,851",
        "Mar 2022": "53,274",
        "Mar 2023": "51,451",
        "Mar 2024": "63,016",
        "Mar 2025": "69,297"
      },
      "CWIP": {
        "Mar 2014": "3,660",
        "Mar 2015": "191",
        "Mar 2016": "88",
        "Mar 2017": "125",
        "Mar 2018": "120",
        "Mar 2019": "350",
        "Mar 2020": "2,347",
        "Mar 2021": "6,439",
        "Mar 2022": "10,270",
        "Mar 2023": "12,880",
        "Mar 2024": "925",
        "Mar 2025": "12,104"
      },
      "Investments": {
        "Mar 2014": "115",
        "Mar 2015": "357",
        "Mar 2016": "0",
        "Mar 2017": "164",
        "Mar 2018": "0",
        "Mar 2019": "3",
        "Mar 2020": "3",
        "Mar 2021": "20",
        "Mar 2022": "183",
        "Mar 2023": "654",
        "Mar 2024": "374",
        "Mar 2025": "1,097"
      },
      "Other Assets+": {
        "Mar 2014": "8,599",
        "Mar 2015": "12,846",
        "Mar 2016": "18,765",
        "Mar 2017": "16,831",
        "Mar 2018": "17,271",
        "Mar 2019": "17,213",
        "Mar 2020": "16,830",
        "Mar 2021": "19,495",
        "Mar 2022": "18,254",
        "Mar 2023": "20,836",
        "Mar 2024": "27,694",
        "Mar 2025": "30,418"
      },
      "Total Assets": {
        "Mar 2014": "58,739",
        "Mar 2015": "58,474",
        "Mar 2016": "75,794",
        "Mar 2017": "71,511",
        "Mar 2018": "69,528",
        "Mar 2019": "67,985",
        "Mar 2020": "75,025",
        "Mar 2021": "78,806",
        "Mar 2022": "81,981",
        "Mar 2023": "85,821",
        "Mar 2024": "92,009",
        "Mar 2025": "112,918"
      }
    },
    "cash_flow": {
      "Cash from Operating Activity+": {
        "Mar 2014": "3,238",
        "Mar 2015": "5,824",
        "Mar 2016": "5,257",
        "Mar 2017": "4,725",
        "Mar 2018": "5,101",
        "Mar 2019": "5,610",
        "Mar 2020": "5,598",
        "Mar 2021": "7,014",
        "Mar 2022": "10,233",
        "Mar 2023": "8,431",
        "Mar 2024": "14,170",
        "Mar 2025": "21,501"
      },
      "Cash from Investing Activity+": {
        "Mar 2014": "-4,700",
        "Mar 2015": "-4,737",
        "Mar 2016": "-2,692",
        "Mar 2017": "-1,212",
        "Mar 2018": "-520",
        "Mar 2019": "-984",
        "Mar 2020": "-2,304",
        "Mar 2021": "-2,188",
        "Mar 2022": "774",
        "Mar 2023": "1,545",
        "Mar 2024": "3,481",
        "Mar 2025": "-17,142"
      },
      "Cash from Financing Activity+": {
        "Mar 2014": "1,631",
        "Mar 2015": "-1,144",
        "Mar 2016": "-2,713",
        "Mar 2017": "-3,539",
        "Mar 2018": "-4,600",
        "Mar 2019": "-4,663",
        "Mar 2020": "-2,377",
        "Mar 2021": "-5,655",
        "Mar 2022": "-10,338",
        "Mar 2023": "-10,408",
        "Mar 2024": "-16,864",
        "Mar 2025": "-5,175"
      },
      "Net Cash Flow": {
        "Mar 2014": "169",
        "Mar 2015": "-58",
        "Mar 2016": "-148",
        "Mar 2017": "-26",
        "Mar 2018": "-19",
        "Mar 2019": "-37",
        "Mar 2020": "917",
        "Mar 2021": "-828",
        "Mar 2022": "669",
        "Mar 2023": "-433",
        "Mar 2024": "787",
        "Mar 2025": "-816"
      }
    },
    "ratios": {
      "Debtor Days": {
        "Mar 2014": "37",
        "Mar 2015": "68",
        "Mar 2016": "179",
        "Mar 2017": "124",
        "Mar 2018": "109",
        "Mar 2019": "131",
        "Mar 2020": "115",
        "Mar 2021": "165",
        "Mar 2022": "126",
        "Mar 2023": "109",
        "Mar 2024": "85",
        "Mar 2025": "85"
      },
      "Inventory Days": {
        "Mar 2014": "",
        "Mar 2015": "",
        "Mar 2016": "",
        "Mar 2017": "",
        "Mar 2018": "",
        "Mar 2019": "",
        "Mar 2020": "",
        "Mar 2021": "",
        "Mar 2022": "",
        "Mar 2023": "",
        "Mar 2024": "",
        "Mar 2025": ""
      },
      "Days Payable": {
        "Mar 2014": "",
        "Mar 2015": "",
        "Mar 2016": "",
        "Mar 2017": "",
        "Mar 2018": "",
        "Mar 2019": "",
        "Mar 2020": "",
        "Mar 2021": "",
        "Mar 2022": "",
        "Mar 2023": "",
        "Mar 2024": "",
        "Mar 2025": ""
      },
      "Cash Conversion Cycle": {
        "Mar 2014": "37",
        "Mar 2015": "68",
        "Mar 2016": "179",
        "Mar 2017": "124",
        "Mar 2018": "109",
        "Mar 2019": "131",
        "Mar 2020": "115",
        "Mar 2021": "165",
        "Mar 2022": "126",
        "Mar 2023": "109",
        "Mar 2024": "85",
        "Mar 2025": "85"
      },
      "Working Capital Days": {
        "Mar 2014": "-289",
        "Mar 2015": "-161",
        "Mar 2016": "-154",
        "Mar 2017": "-208",
        "Mar 2018": "-269",
        "Mar 2019": "-90",
        "Mar 2020": "-77",
        "Mar 2021": "-38",
        "Mar 2022": "-46",
        "Mar 2023": "-6",
        "Mar 2024": "16",
        "Mar 2025": "18"
      },
      "ROCE %": {
        "Mar 2014": "6%",
        "Mar 2015": "7%",
        "Mar 2016": "11%",
        "Mar 2017": "6%",
        "Mar 2018": "6%",
        "Mar 2019": "9%",
        "Mar 2020": "7%",
        "Mar 2021": "12%",
        "Mar 2022": "16%",
        "Mar 2023": "16%",
        "Mar 2024": "32%",
        "Mar 2025": "23%"
      }
    },
    "shareholding_pattern": {
      "Sep 2022": {
        "Promoters+": "74.97",
        "FIIs+": "13.23",
        "DIIs+": "0.00",
        "Public+": "11.80"
      },
      "Dec 2022": {
        "Promoters+": "74.97",
        "FIIs+": "12.88",
        "DIIs+": "0.00",
        "Public+": "12.15"
      },
      "Mar 2023": {
        "Promoters+": "74.97",
        "FIIs+": "11.70",
        "DIIs+": "0.01",
        "Public+": "13.32"
      },
      "Jun 2023": {
        "Promoters+": "74.97",
        "FIIs+": "11.95",
        "DIIs+": "0.04",
        "Public+": "13.04"
      },
      "Sep 2023": {
        "Promoters+": "70.02",
        "FIIs+": "17.51",
        "DIIs+": "0.76",
        "Public+": "11.72"
      },
      "Dec 2023": {
        "Promoters+": "71.75",
        "FIIs+": "15.86",
        "DIIs+": "1.18",
        "Public+": "11.20"
      },
      "Mar 2024": {
        "Promoters+": "71.75",
        "FIIs+": "15.91",
        "DIIs+": "1.41",
        "Public+": "10.93"
      },
      "Jun 2024": {
        "Promoters+": "72.71",
        "FIIs+": "14.73",
        "DIIs+": "1.42",
        "Public+": "11.14"
      },
      "Sep 2024": {
        "Promoters+": "74.96",
        "FIIs+": "12.66",
        "DIIs+": "1.52",
        "Public+": "10.84"
      },
      "Dec 2024": {
        "Promoters+": "74.96",
        "FIIs+": "12.34",
        "DIIs+": "1.60",
        "Public+": "11.09"
      },
      "Mar 2025": {
        "Promoters+": "74.96",
        "FIIs+": "12.36",
        "DIIs+": "1.64",
        "Public+": "11.03"
      },
      "Jun 2025": {
        "Promoters+": "74.96",
        "FIIs+": "12.46",
        "DIIs+": "1.76",
        "Public+": "10.82"
      },
      "Mar 2017": {
        "Promoters+": "68.08",
        "FIIs+": "22.12",
        "DIIs+": "2.67",
        "Public+": "7.12"
      },
      "Mar 2018": {
        "Promoters+": "73.07",
        "FIIs+": "11.28",
        "DIIs+": "9.14",
        "Public+": "6.51"
      },
      "Mar 2019": {
        "Promoters+": "74.97",
        "FIIs+": "10.02",
        "DIIs+": "10.11",
        "Public+": "4.90"
      },
      "Mar 2020": {
        "Promoters+": "74.97",
        "FIIs+": "12.38",
        "DIIs+": "8.29",
        "Public+": "4.35"
      },
      "Mar 2021": {
        "Promoters+": "74.97",
        "FIIs+": "11.52",
        "DIIs+": "7.08",
        "Public+": "6.43"
      },
      "Mar 2022": {
        "Promoters+": "74.97",
        "FIIs+": "11.31",
        "DIIs+": "5.56",
        "Public+": "8.15"
      }
    }
  },
  {
    "timestamp": "2025-09-22 11:39:53",
    "scan_id": "20250922_113605",
    "ticker": "ADANIPOWER",
    "quarterly_results": {
      "Sales+": {
        "Jun 2022": "13,723",
        "Sep 2022": "7,044",
        "Dec 2022": "7,764",
        "Mar 2023": "10,242",
        "Jun 2023": "11,006",
        "Sep 2023": "12,991",
        "Dec 2023": "12,991",
        "Mar 2024": "13,364",
        "Jun 2024": "14,956",
        "Sep 2024": "13,339",
        "Dec 2024": "13,671",
        "Mar 2025": "14,237",
        "Jun 2025": "14,109"
      },
      "Expenses+": {
        "Jun 2022": "8,003",
        "Sep 2022": "6,096",
        "Dec 2022": "6,295",
        "Mar 2023": "8,335",
        "Jun 2023": "7,491",
        "Sep 2023": "7,819",
        "Dec 2023": "8,346",
        "Mar 2024": "8,514",
        "Jun 2024": "8,761",
        "Sep 2024": "8,063",
        "Dec 2024": "8,648",
        "Mar 2025": "9,425",
        "Jun 2025": "8,424"
      },
      "Operating Profit": {
        "Jun 2022": "5,720",
        "Sep 2022": "948",
        "Dec 2022": "1,470",
        "Mar 2023": "1,907",
        "Jun 2023": "3,514",
        "Sep 2023": "5,171",
        "Dec 2023": "4,645",
        "Mar 2024": "4,850",
        "Jun 2024": "6,194",
        "Sep 2024": "5,276",
        "Dec 2024": "5,023",
        "Mar 2025": "4,813",
        "Jun 2025": "5,685"
      },
      "OPM %": {
        "Jun 2022": "42%",
        "Sep 2022": "13%",
        "Dec 2022": "19%",
        "Mar 2023": "19%",
        "Jun 2023": "32%",
        "Sep 2023": "40%",
        "Dec 2023": "36%",
        "Mar 2024": "36%",
        "Jun 2024": "41%",
        "Sep 2024": "40%",
        "Dec 2024": "37%",
        "Mar 2025": "34%",
        "Jun 2025": "40%"
      },
      "Other Income+": {
        "Jun 2022": "1,786",
        "Sep 2022": "1,402",
        "Dec 2022": "526",
        "Mar 2023": "553",
        "Jun 2023": "7,103",
        "Sep 2023": "1,945",
        "Dec 2023": "364",
        "Mar 2024": "518",
        "Jun 2024": "518",
        "Sep 2024": "724",
        "Dec 2024": "1,162",
        "Mar 2025": "298",
        "Jun 2025": "465"
      },
      "Interest": {
        "Jun 2022": "823",
        "Sep 2022": "818",
        "Dec 2022": "946",
        "Mar 2023": "746",
        "Jun 2023": "883",
        "Sep 2023": "888",
        "Dec 2023": "797",
        "Mar 2024": "820",
        "Jun 2024": "811",
        "Sep 2024": "807",
        "Dec 2024": "957",
        "Mar 2025": "765",
        "Jun 2025": "857"
      },
      "Depreciation": {
        "Jun 2022": "816",
        "Sep 2022": "833",
        "Dec 2022": "838",
        "Mar 2023": "817",
        "Jun 2023": "935",
        "Sep 2023": "1,004",
        "Dec 2023": "1,002",
        "Mar 2024": "990",
        "Jun 2024": "996",
        "Sep 2024": "1,059",
        "Dec 2024": "1,170",
        "Mar 2025": "1,085",
        "Jun 2025": "1,089"
      },
      "Profit before tax": {
        "Jun 2022": "5,866",
        "Sep 2022": "699",
        "Dec 2022": "212",
        "Mar 2023": "898",
        "Jun 2023": "8,800",
        "Sep 2023": "5,224",
        "Dec 2023": "3,210",
        "Mar 2024": "3,558",
        "Jun 2024": "4,906",
        "Sep 2024": "4,134",
        "Dec 2024": "4,059",
        "Mar 2025": "3,261",
        "Jun 2025": "4,204"
      },
      "Tax %": {
        "Jun 2022": "19%",
        "Sep 2022": "0%",
        "Dec 2022": "96%",
        "Mar 2023": "-484%",
        "Jun 2023": "0%",
        "Sep 2023": "-26%",
        "Dec 2023": "15%",
        "Mar 2024": "23%",
        "Jun 2024": "20%",
        "Sep 2024": "20%",
        "Dec 2024": "28%",
        "Mar 2025": "20%",
        "Jun 2025": "21%"
      },
      "Net Profit+": {
        "Jun 2022": "4,780",
        "Sep 2022": "696",
        "Dec 2022": "9",
        "Mar 2023": "5,242",
        "Jun 2023": "8,759",
        "Sep 2023": "6,594",
        "Dec 2023": "2,738",
        "Mar 2024": "2,737",
        "Jun 2024": "3,913",
        "Sep 2024": "3,298",
        "Dec 2024": "2,940",
        "Mar 2025": "2,599",
        "Jun 2025": "3,305"
      },
      "EPS in Rs": {
        "Jun 2022": "2.48",
        "Sep 2022": "0.36",
        "Dec 2022": "0.00",
        "Mar 2023": "2.72",
        "Jun 2023": "4.54",
        "Sep 2023": "3.42",
        "Dec 2023": "1.42",
        "Mar 2024": "1.42",
        "Jun 2024": "2.03",
        "Sep 2024": "1.73",
        "Dec 2024": "1.59",
        "Mar 2025": "1.37",
        "Jun 2025": "1.76"
      },
      "Raw PDF": {
        "Jun 2022": "",
        "Sep 2022": "",
        "Dec 2022": "",
        "Mar 2023": "",
        "Jun 2023": "",
        "Sep 2023": "",
        "Dec 2023": "",
        "Mar 2024": "",
        "Jun 2024": "",
        "Sep 2024": "",
        "Dec 2024": "",
        "Mar 2025": "",
        "Jun 2025": ""
      }
    },
    "balance_sheet": {
      "Equity Capital": {
        "Mar 2014": "2,872",
        "Mar 2015": "2,872",
        "Mar 2016": "3,334",
        "Mar 2017": "3,857",
        "Mar 2018": "3,857",
        "Mar 2019": "3,857",
        "Mar 2020": "3,857",
        "Mar 2021": "3,857",
        "Mar 2022": "3,857",
        "Mar 2023": "3,857",
        "Mar 2024": "3,857",
        "Mar 2025": "3,857"
      },
      "Reserves": {
        "Mar 2014": "3,671",
        "Mar 2015": "2,853",
        "Mar 2016": "4,134",
        "Mar 2017": "-857",
        "Mar 2018": "-2,968",
        "Mar 2019": "3,855",
        "Mar 2020": "2,624",
        "Mar 2021": "9,256",
        "Mar 2022": "14,600",
        "Mar 2023": "26,019",
        "Mar 2024": "39,042",
        "Mar 2025": "52,490"
      },
      "Borrowings+": {
        "Mar 2014": "44,150",
        "Mar 2015": "44,742",
        "Mar 2016": "52,729",
        "Mar 2017": "52,484",
        "Mar 2018": "52,835",
        "Mar 2019": "46,980",
        "Mar 2020": "55,199",
        "Mar 2021": "52,519",
        "Mar 2022": "49,145",
        "Mar 2023": "42,350",
        "Mar 2024": "34,862",
        "Mar 2025": "39,495"
      },
      "Other Liabilities+": {
        "Mar 2014": "8,045",
        "Mar 2015": "8,008",
        "Mar 2016": "15,597",
        "Mar 2017": "16,027",
        "Mar 2018": "15,804",
        "Mar 2019": "13,293",
        "Mar 2020": "13,346",
        "Mar 2021": "13,175",
        "Mar 2022": "14,379",
        "Mar 2023": "13,596",
        "Mar 2024": "14,248",
        "Mar 2025": "17,076"
      },
      "Total Liabilities": {
        "Mar 2014": "58,739",
        "Mar 2015": "58,474",
        "Mar 2016": "75,794",
        "Mar 2017": "71,511",
        "Mar 2018": "69,528",
        "Mar 2019": "67,985",
        "Mar 2020": "75,025",
        "Mar 2021": "78,806",
        "Mar 2022": "81,981",
        "Mar 2023": "85,821",
        "Mar 2024": "92,009",
        "Mar 2025": "112,918"
      },
      "Fixed Assets+": {
        "Mar 2014": "46,365",
        "Mar 2015": "45,080",
        "Mar 2016": "56,941",
        "Mar 2017": "54,391",
        "Mar 2018": "52,137",
        "Mar 2019": "50,419",
        "Mar 2020": "55,846",
        "Mar 2021": "52,851",
        "Mar 2022": "53,274",
        "Mar 2023": "51,451",
        "Mar 2024": "63,016",
        "Mar 2025": "69,297"
      },
      "CWIP": {
        "Mar 2014": "3,660",
        "Mar 2015": "191",
        "Mar 2016": "88",
        "Mar 2017": "125",
        "Mar 2018": "120",
        "Mar 2019": "350",
        "Mar 2020": "2,347",
        "Mar 2021": "6,439",
        "Mar 2022": "10,270",
        "Mar 2023": "12,880",
        "Mar 2024": "925",
        "Mar 2025": "12,104"
      },
      "Investments": {
        "Mar 2014": "115",
        "Mar 2015": "357",
        "Mar 2016": "0",
        "Mar 2017": "164",
        "Mar 2018": "0",
        "Mar 2019": "3",
        "Mar 2020": "3",
        "Mar 2021": "20",
        "Mar 2022": "183",
        "Mar 2023": "654",
        "Mar 2024": "374",
        "Mar 2025": "1,097"
      },
      "Other Assets+": {
        "Mar 2014": "8,599",
        "Mar 2015": "12,846",
        "Mar 2016": "18,765",
        "Mar 2017": "16,831",
        "Mar 2018": "17,271",
        "Mar 2019": "17,213",
        "Mar 2020": "16,830",
        "Mar 2021": "19,495",
        "Mar 2022": "18,254",
        "Mar 2023": "20,836",
        "Mar 2024": "27,694",
        "Mar 2025": "30,418"
      },
      "Total Assets": {
        "Mar 2014": "58,739",
        "Mar 2015": "58,474",
        "Mar 2016": "75,794",
        "Mar 2017": "71,511",
        "Mar 2018": "69,528",
        "Mar 2019": "67,985",
        "Mar 2020": "75,025",
        "Mar 2021": "78,806",
        "Mar 2022": "81,981",
        "Mar 2023": "85,821",
        "Mar 2024": "92,009",
        "Mar 2025": "112,918"
      }
    },
    "cash_flow": {
      "Cash from Operating Activity+": {
        "Mar 2014": "3,238",
        "Mar 2015": "5,824",
        "Mar 2016": "5,257",
        "Mar 2017": "4,725",
        "Mar 2018": "5,101",
        "Mar 2019": "5,610",
        "Mar 2020": "5,598",
        "Mar 2021": "7,014",
        "Mar 2022": "10,233",
        "Mar 2023": "8,431",
        "Mar 2024": "14,170",
        "Mar 2025": "21,501"
      },
      "Cash from Investing Activity+": {
        "Mar 2014": "-4,700",
        "Mar 2015": "-4,737",
        "Mar 2016": "-2,692",
        "Mar 2017": "-1,212",
        "Mar 2018": "-520",
        "Mar 2019": "-984",
        "Mar 2020": "-2,304",
        "Mar 2021": "-2,188",
        "Mar 2022": "774",
        "Mar 2023": "1,545",
        "Mar 2024": "3,481",
        "Mar 2025": "-17,142"
      },
      "Cash from Financing Activity+": {
        "Mar 2014": "1,631",
        "Mar 2015": "-1,144",
        "Mar 2016": "-2,713",
        "Mar 2017": "-3,539",
        "Mar 2018": "-4,600",
        "Mar 2019": "-4,663",
        "Mar 2020": "-2,377",
        "Mar 2021": "-5,655",
        "Mar 2022": "-10,338",
        "Mar 2023": "-10,408",
        "Mar 2024": "-16,864",
        "Mar 2025": "-5,175"
      },
      "Net Cash Flow": {
        "Mar 2014": "169",
        "Mar 2015": "-58",
        "Mar 2016": "-148",
        "Mar 2017": "-26",
        "Mar 2018": "-19",
        "Mar 2019": "-37",
        "Mar 2020": "917",
        "Mar 2021": "-828",
        "Mar 2022": "669",
        "Mar 2023": "-433",
        "Mar 2024": "787",
        "Mar 2025": "-816"
      }
    },
    "ratios": {
      "Debtor Days": {
        "Mar 2014": "37",
        "Mar 2015": "68",
        "Mar 2016": "179",
        "Mar 2017": "124",
        "Mar 2018": "109",
        "Mar 2019": "131",
        "Mar 2020": "115",
        "Mar 2021": "165",
        "Mar 2022": "126",
        "Mar 2023": "109",
        "Mar 2024": "85",
        "Mar 2025": "85"
      },
      "Inventory Days": {
        "Mar 2014": "",
        "Mar 2015": "",
        "Mar 2016": "",
        "Mar 2017": "",
        "Mar 2018": "",
        "Mar 2019": "",
        "Mar 2020": "",
        "Mar 2021": "",
        "Mar 2022": "",
        "Mar 2023": "",
        "Mar 2024": "",
        "Mar 2025": ""
      },
      "Days Payable": {
        "Mar 2014": "",
        "Mar 2015": "",
        "Mar 2016": "",
        "Mar 2017": "",
        "Mar 2018": "",
        "Mar 2019": "",
        "Mar 2020": "",
        "Mar 2021": "",
        "Mar 2022": "",
        "Mar 2023": "",
        "Mar 2024": "",
        "Mar 2025": ""
      },
      "Cash Conversion Cycle": {
        "Mar 2014": "37",
        "Mar 2015": "68",
        "Mar 2016": "179",
        "Mar 2017": "124",
        "Mar 2018": "109",
        "Mar 2019": "131",
        "Mar 2020": "115",
        "Mar 2021": "165",
        "Mar 2022": "126",
        "Mar 2023": "109",
        "Mar 2024": "85",
        "Mar 2025": "85"
      },
      "Working Capital Days": {
        "Mar 2014": "-289",
        "Mar 2015": "-161",
        "Mar 2016": "-154",
        "Mar 2017": "-208",
        "Mar 2018": "-269",
        "Mar 2019": "-90",
        "Mar 2020": "-77",
        "Mar 2021": "-38",
        "Mar 2022": "-46",
        "Mar 2023": "-6",
        "Mar 2024": "16",
        "Mar 2025": "18"
      },
      "ROCE %": {
        "Mar 2014": "6%",
        "Mar 2015": "7%",
        "Mar 2016": "11%",
        "Mar 2017": "6%",
        "Mar 2018": "6%",
        "Mar 2019": "9%",
        "Mar 2020": "7%",
        "Mar 2021": "12%",
        "Mar 2022": "16%",
        "Mar 2023": "16%",
        "Mar 2024": "32%",
        "Mar 2025": "23%"
      }
    },
    "shareholding_pattern": {
      "Sep 2022": {
        "Promoters+": "74.97",
        "FIIs+": "13.23",
        "DIIs+": "0.00",
        "Public+": "11.80"
      },
      "Dec 2022": {
        "Promoters+": "74.97",
        "FIIs+": "12.88",
        "DIIs+": "0.00",
        "Public+": "12.15"
      },
      "Mar 2023": {
        "Promoters+": "74.97",
        "FIIs+": "11.70",
        "DIIs+": "0.01",
        "Public+": "13.32"
      },
      "Jun 2023": {
        "Promoters+": "74.97",
        "FIIs+": "11.95",
        "DIIs+": "0.04",
        "Public+": "13.04"
      },
      "Sep 2023": {
        "Promoters+": "70.02",
        "FIIs+": "17.51",
        "DIIs+": "0.76",
        "Public+": "11.72"
      },
      "Dec 2023": {
        "Promoters+": "71.75",
        "FIIs+": "15.86",
        "DIIs+": "1.18",
        "Public+": "11.20"
      },
      "Mar 2024": {
        "Promoters+": "71.75",
        "FIIs+": "15.91",
        "DIIs+": "1.41",
        "Public+": "10.93"
      },
      "Jun 2024": {
        "Promoters+": "72.71",
        "FIIs+": "14.73",
        "DIIs+": "1.42",
        "Public+": "11.14"
      },
      "Sep 2024": {
        "Promoters+": "74.96",
        "FIIs+": "12.66",
        "DIIs+": "1.52",
        "Public+": "10.84"
      },
      "Dec 2024": {
        "Promoters+": "74.96",
        "FIIs+": "12.34",
        "DIIs+": "1.60",
        "Public+": "11.09"
      },
      "Mar 2025": {
        "Promoters+": "74.96",
        "FIIs+": "12.36",
        "DIIs+": "1.64",
        "Public+": "11.03"
      },
      "Jun 2025": {
        "Promoters+": "74.96",
        "FIIs+": "12.46",
        "DIIs+": "1.76",
        "Public+": "10.82"
      },
      "Mar 2017": {
        "Promoters+": "68.08",
        "FIIs+": "22.12",
        "DIIs+": "2.67",
        "Public+": "7.12"
      },
      "Mar 2018": {
        "Promoters+": "73.07",
        "FIIs+": "11.28",
        "DIIs+": "9.14",
        "Public+": "6.51"
      },
      "Mar 2019": {
        "Promoters+": "74.97",
        "FIIs+": "10.02",
        "DIIs+": "10.11",
        "Public+": "4.90"
      },
      "Mar 2020": {
        "Promoters+": "74.97",
        "FIIs+": "12.38",
        "DIIs+": "8.29",
        "Public+": "4.35"
      },
      "Mar 2021": {
        "Promoters+": "74.97",
        "FIIs+": "11.52",
        "DIIs+": "7.08",
        "Public+": "6.43"
      },
      "Mar 2022": {
        "Promoters+": "74.97",
        "FIIs+": "11.31",
        "DIIs+": "5.56",
        "Public+": "8.15"
      }
    }
  },
  {
    "timestamp": "2025-09-24 01:48:30",
    "scan_id": "20250923_111955",
    "ticker": "ADANIPOWER",
    "quarterly_results": {
      "Sales+": {
        "Jun 2022": "13,723",
        "Sep 2022": "7,044",
        "Dec 2022": "7,764",
        "Mar 2023": "10,242",
        "Jun 2023": "11,006",
        "Sep 2023": "12,991",
        "Dec 2023": "12,991",
        "Mar 2024": "13,364",
        "Jun 2024": "14,956",
        "Sep 2024": "13,339",
        "Dec 2024": "13,671",
        "Mar 2025": "14,237",
        "Jun 2025": "14,109"
      },
      "Expenses+": {
        "Jun 2022": "8,003",
        "Sep 2022": "6,096",
        "Dec 2022": "6,295",
        "Mar 2023": "8,335",
        "Jun 2023": "7,491",
        "Sep 2023": "7,819",
        "Dec 2023": "8,346",
        "Mar 2024": "8,514",
        "Jun 2024": "8,761",
        "Sep 2024": "8,063",
        "Dec 2024": "8,648",
        "Mar 2025": "9,425",
        "Jun 2025": "8,424"
      },
      "Operating Profit": {
        "Jun 2022": "5,720",
        "Sep 2022": "948",
        "Dec 2022": "1,470",
        "Mar 2023": "1,907",
        "Jun 2023": "3,514",
        "Sep 2023": "5,171",
        "Dec 2023": "4,645",
        "Mar 2024": "4,850",
        "Jun 2024": "6,194",
        "Sep 2024": "5,276",
        "Dec 2024": "5,023",
        "Mar 2025": "4,813",
        "Jun 2025": "5,685"
      },
      "OPM %": {
        "Jun 2022": "42%",
        "Sep 2022": "13%",
        "Dec 2022": "19%",
        "Mar 2023": "19%",
        "Jun 2023": "32%",
        "Sep 2023": "40%",
        "Dec 2023": "36%",
        "Mar 2024": "36%",
        "Jun 2024": "41%",
        "Sep 2024": "40%",
        "Dec 2024": "37%",
        "Mar 2025": "34%",
        "Jun 2025": "40%"
      },
      "Other Income+": {
        "Jun 2022": "1,786",
        "Sep 2022": "1,402",
        "Dec 2022": "526",
        "Mar 2023": "553",
        "Jun 2023": "7,103",
        "Sep 2023": "1,945",
        "Dec 2023": "364",
        "Mar 2024": "518",
        "Jun 2024": "518",
        "Sep 2024": "724",
        "Dec 2024": "1,162",
        "Mar 2025": "298",
        "Jun 2025": "465"
      },
      "Interest": {
        "Jun 2022": "823",
        "Sep 2022": "818",
        "Dec 2022": "946",
        "Mar 2023": "746",
        "Jun 2023": "883",
        "Sep 2023": "888",
        "Dec 2023": "797",
        "Mar 2024": "820",
        "Jun 2024": "811",
        "Sep 2024": "807",
        "Dec 2024": "957",
        "Mar 2025": "765",
        "Jun 2025": "857"
      },
      "Depreciation": {
        "Jun 2022": "816",
        "Sep 2022": "833",
        "Dec 2022": "838",
        "Mar 2023": "817",
        "Jun 2023": "935",
        "Sep 2023": "1,004",
        "Dec 2023": "1,002",
        "Mar 2024": "990",
        "Jun 2024": "996",
        "Sep 2024": "1,059",
        "Dec 2024": "1,170",
        "Mar 2025": "1,085",
        "Jun 2025": "1,089"
      },
      "Profit before tax": {
        "Jun 2022": "5,866",
        "Sep 2022": "699",
        "Dec 2022": "212",
        "Mar 2023": "898",
        "Jun 2023": "8,800",
        "Sep 2023": "5,224",
        "Dec 2023": "3,210",
        "Mar 2024": "3,558",
        "Jun 2024": "4,906",
        "Sep 2024": "4,134",
        "Dec 2024": "4,059",
        "Mar 2025": "3,261",
        "Jun 2025": "4,204"
      },
      "Tax %": {
        "Jun 2022": "19%",
        "Sep 2022": "0%",
        "Dec 2022": "96%",
        "Mar 2023": "-484%",
        "Jun 2023": "0%",
        "Sep 2023": "-26%",
        "Dec 2023": "15%",
        "Mar 2024": "23%",
        "Jun 2024": "20%",
        "Sep 2024": "20%",
        "Dec 2024": "28%",
        "Mar 2025": "20%",
        "Jun 2025": "21%"
      },
      "Net Profit+": {
        "Jun 2022": "4,780",
        "Sep 2022": "696",
        "Dec 2022": "9",
        "Mar 2023": "5,242",
        "Jun 2023": "8,759",
        "Sep 2023": "6,594",
        "Dec 2023": "2,738",
        "Mar 2024": "2,737",
        "Jun 2024": "3,913",
        "Sep 2024": "3,298",
        "Dec 2024": "2,940",
        "Mar 2025": "2,599",
        "Jun 2025": "3,305"
      },
      "EPS in Rs": {
        "Jun 2022": "2.48",
        "Sep 2022": "0.36",
        "Dec 2022": "0.00",
        "Mar 2023": "2.72",
        "Jun 2023": "4.54",
        "Sep 2023": "3.42",
        "Dec 2023": "1.42",
        "Mar 2024": "1.42",
        "Jun 2024": "2.03",
        "Sep 2024": "1.73",
        "Dec 2024": "1.59",
        "Mar 2025": "1.37",
        "Jun 2025": "1.76"
      },
      "Raw PDF": {
        "Jun 2022": "",
        "Sep 2022": "",
        "Dec 2022": "",
        "Mar 2023": "",
        "Jun 2023": "",
        "Sep 2023": "",
        "Dec 2023": "",
        "Mar 2024": "",
        "Jun 2024": "",
        "Sep 2024": "",
        "Dec 2024": "",
        "Mar 2025": "",
        "Jun 2025": ""
      }
    },
    "balance_sheet": {
      "Equity Capital": {
        "Mar 2014": "2,872",
        "Mar 2015": "2,872",
        "Mar 2016": "3,334",
        "Mar 2017": "3,857",
        "Mar 2018": "3,857",
        "Mar 2019": "3,857",
        "Mar 2020": "3,857",
        "Mar 2021": "3,857",
        "Mar 2022": "3,857",
        "Mar 2023": "3,857",
        "Mar 2024": "3,857",
        "Mar 2025": "3,857"
      },
      "Reserves": {
        "Mar 2014": "3,671",
        "Mar 2015": "2,853",
        "Mar 2016": "4,134",
        "Mar 2017": "-857",
        "Mar 2018": "-2,968",
        "Mar 2019": "3,855",
        "Mar 2020": "2,624",
        "Mar 2021": "9,256",
        "Mar 2022": "14,600",
        "Mar 2023": "26,019",
        "Mar 2024": "39,042",
        "Mar 2025": "52,490"
      },
      "Borrowings+": {
        "Mar 2014": "44,150",
        "Mar 2015": "44,742",
        "Mar 2016": "52,729",
        "Mar 2017": "52,484",
        "Mar 2018": "52,835",
        "Mar 2019": "46,980",
        "Mar 2020": "55,199",
        "Mar 2021": "52,519",
        "Mar 2022": "49,145",
        "Mar 2023": "42,350",
        "Mar 2024": "34,862",
        "Mar 2025": "39,495"
      },
      "Other Liabilities+": {
        "Mar 2014": "8,045",
        "Mar 2015": "8,008",
        "Mar 2016": "15,597",
        "Mar 2017": "16,027",
        "Mar 2018": "15,804",
        "Mar 2019": "13,293",
        "Mar 2020": "13,346",
        "Mar 2021": "13,175",
        "Mar 2022": "14,379",
        "Mar 2023": "13,596",
        "Mar 2024": "14,248",
        "Mar 2025": "17,076"
      },
      "Total Liabilities": {
        "Mar 2014": "58,739",
        "Mar 2015": "58,474",
        "Mar 2016": "75,794",
        "Mar 2017": "71,511",
        "Mar 2018": "69,528",
        "Mar 2019": "67,985",
        "Mar 2020": "75,025",
        "Mar 2021": "78,806",
        "Mar 2022": "81,981",
        "Mar 2023": "85,821",
        "Mar 2024": "92,009",
        "Mar 2025": "112,918"
      },
      "Fixed Assets+": {
        "Mar 2014": "46,365",
        "Mar 2015": "45,080",
        "Mar 2016": "56,941",
        "Mar 2017": "54,391",
        "Mar 2018": "52,137",
        "Mar 2019": "50,419",
        "Mar 2020": "55,846",
        "Mar 2021": "52,851",
        "Mar 2022": "53,274",
        "Mar 2023": "51,451",
        "Mar 2024": "63,016",
        "Mar 2025": "69,297"
      },
      "CWIP": {
        "Mar 2014": "3,660",
        "Mar 2015": "191",
        "Mar 2016": "88",
        "Mar 2017": "125",
        "Mar 2018": "120",
        "Mar 2019": "350",
        "Mar 2020": "2,347",
        "Mar 2021": "6,439",
        "Mar 2022": "10,270",
        "Mar 2023": "12,880",
        "Mar 2024": "925",
        "Mar 2025": "12,104"
      },
      "Investments": {
        "Mar 2014": "115",
        "Mar 2015": "357",
        "Mar 2016": "0",
        "Mar 2017": "164",
        "Mar 2018": "0",
        "Mar 2019": "3",
        "Mar 2020": "3",
        "Mar 2021": "20",
        "Mar 2022": "183",
        "Mar 2023": "654",
        "Mar 2024": "374",
        "Mar 2025": "1,097"
      },
      "Other Assets+": {
        "Mar 2014": "8,599",
        "Mar 2015": "12,846",
        "Mar 2016": "18,765",
        "Mar 2017": "16,831",
        "Mar 2018": "17,271",
        "Mar 2019": "17,213",
        "Mar 2020": "16,830",
        "Mar 2021": "19,495",
        "Mar 2022": "18,254",
        "Mar 2023": "20,836",
        "Mar 2024": "27,694",
        "Mar 2025": "30,418"
      },
      "Total Assets": {
        "Mar 2014": "58,739",
        "Mar 2015": "58,474",
        "Mar 2016": "75,794",
        "Mar 2017": "71,511",
        "Mar 2018": "69,528",
        "Mar 2019": "67,985",
        "Mar 2020": "75,025",
        "Mar 2021": "78,806",
        "Mar 2022": "81,981",
        "Mar 2023": "85,821",
        "Mar 2024": "92,009",
        "Mar 2025": "112,918"
      }
    },
    "cash_flow": {
      "Cash from Operating Activity+": {
        "Mar 2014": "3,238",
        "Mar 2015": "5,824",
        "Mar 2016": "5,257",
        "Mar 2017": "4,725",
        "Mar 2018": "5,101",
        "Mar 2019": "5,610",
        "Mar 2020": "5,598",
        "Mar 2021": "7,014",
        "Mar 2022": "10,233",
        "Mar 2023": "8,431",
        "Mar 2024": "14,170",
        "Mar 2025": "21,501"
      },
      "Cash from Investing Activity+": {
        "Mar 2014": "-4,700",
        "Mar 2015": "-4,737",
        "Mar 2016": "-2,692",
        "Mar 2017": "-1,212",
        "Mar 2018": "-520",
        "Mar 2019": "-984",
        "Mar 2020": "-2,304",
        "Mar 2021": "-2,188",
        "Mar 2022": "774",
        "Mar 2023": "1,545",
        "Mar 2024": "3,481",
        "Mar 2025": "-17,142"
      },
      "Cash from Financing Activity+": {
        "Mar 2014": "1,631",
        "Mar 2015": "-1,144",
        "Mar 2016": "-2,713",
        "Mar 2017": "-3,539",
        "Mar 2018": "-4,600",
        "Mar 2019": "-4,663",
        "Mar 2020": "-2,377",
        "Mar 2021": "-5,655",
        "Mar 2022": "-10,338",
        "Mar 2023": "-10,408",
        "Mar 2024": "-16,864",
        "Mar 2025": "-5,175"
      },
      "Net Cash Flow": {
        "Mar 2014": "169",
        "Mar 2015": "-58",
        "Mar 2016": "-148",
        "Mar 2017": "-26",
        "Mar 2018": "-19",
        "Mar 2019": "-37",
        "Mar 2020": "917",
        "Mar 2021": "-828",
        "Mar 2022": "669",
        "Mar 2023": "-433",
        "Mar 2024": "787",
        "Mar 2025": "-816"
      }
    },
    "ratios": {
      "Debtor Days": {
        "Mar 2014": "37",
        "Mar 2015": "68",
        "Mar 2016": "179",
        "Mar 2017": "124",
        "Mar 2018": "109",
        "Mar 2019": "131",
        "Mar 2020": "115",
        "Mar 2021": "165",
        "Mar 2022": "126",
        "Mar 2023": "109",
        "Mar 2024": "85",
        "Mar 2025": "85"
      },
      "Inventory Days": {
        "Mar 2014": "",
        "Mar 2015": "",
        "Mar 2016": "",
        "Mar 2017": "",
        "Mar 2018": "",
        "Mar 2019": "",
        "Mar 2020": "",
        "Mar 2021": "",
        "Mar 2022": "",
        "Mar 2023": "",
        "Mar 2024": "",
        "Mar 2025": ""
      },
      "Days Payable": {
        "Mar 2014": "",
        "Mar 2015": "",
        "Mar 2016": "",
        "Mar 2017": "",
        "Mar 2018": "",
        "Mar 2019": "",
        "Mar 2020": "",
        "Mar 2021": "",
        "Mar 2022": "",
        "Mar 2023": "",
        "Mar 2024": "",
        "Mar 2025": ""
      },
      "Cash Conversion Cycle": {
        "Mar 2014": "37",
        "Mar 2015": "68",
        "Mar 2016": "179",
        "Mar 2017": "124",
        "Mar 2018": "109",
        "Mar 2019": "131",
        "Mar 2020": "115",
        "Mar 2021": "165",
        "Mar 2022": "126",
        "Mar 2023": "109",
        "Mar 2024": "85",
        "Mar 2025": "85"
      },
      "Working Capital Days": {
        "Mar 2014": "-289",
        "Mar 2015": "-161",
        "Mar 2016": "-154",
        "Mar 2017": "-208",
        "Mar 2018": "-269",
        "Mar 2019": "-90",
        "Mar 2020": "-77",
        "Mar 2021": "-38",
        "Mar 2022": "-46",
        "Mar 2023": "-6",
        "Mar 2024": "16",
        "Mar 2025": "18"
      },
      "ROCE %": {
        "Mar 2014": "6%",
        "Mar 2015": "7%",
        "Mar 2016": "11%",
        "Mar 2017": "6%",
        "Mar 2018": "6%",
        "Mar 2019": "9%",
        "Mar 2020": "7%",
        "Mar 2021": "12%",
        "Mar 2022": "16%",
        "Mar 2023": "16%",
        "Mar 2024": "32%",
        "Mar 2025": "23%"
      }
    },
    "shareholding_pattern": {
      "Sep 2022": {
        "Promoters+": "74.97",
        "FIIs+": "13.23",
        "DIIs+": "0.00",
        "Public+": "11.80"
      },
      "Dec 2022": {
        "Promoters+": "74.97",
        "FIIs+": "12.88",
        "DIIs+": "0.00",
        "Public+": "12.15"
      },
      "Mar 2023": {
        "Promoters+": "74.97",
        "FIIs+": "11.70",
        "DIIs+": "0.01",
        "Public+": "13.32"
      },
      "Jun 2023": {
        "Promoters+": "74.97",
        "FIIs+": "11.95",
        "DIIs+": "0.04",
        "Public+": "13.04"
      },
      "Sep 2023": {
        "Promoters+": "70.02",
        "FIIs+": "17.51",
        "DIIs+": "0.76",
        "Public+": "11.72"
      },
      "Dec 2023": {
        "Promoters+": "71.75",
        "FIIs+": "15.86",
        "DIIs+": "1.18",
        "Public+": "11.20"
      },
      "Mar 2024": {
        "Promoters+": "71.75",
        "FIIs+": "15.91",
        "DIIs+": "1.41",
        "Public+": "10.93"
      },
      "Jun 2024": {
        "Promoters+": "72.71",
        "FIIs+": "14.73",
        "DIIs+": "1.42",
        "Public+": "11.14"
      },
      "Sep 2024": {
        "Promoters+": "74.96",
        "FIIs+": "12.66",
        "DIIs+": "1.52",
        "Public+": "10.84"
      },
      "Dec 2024": {
        "Promoters+": "74.96",
        "FIIs+": "12.34",
        "DIIs+": "1.60",
        "Public+": "11.09"
      },
      "Mar 2025": {
        "Promoters+": "74.96",
        "FIIs+": "12.36",
        "DIIs+": "1.64",
        "Public+": "11.03"
      },
      "Jun 2025": {
        "Promoters+": "74.96",
        "FIIs+": "12.46",
        "DIIs+": "1.76",
        "Public+": "10.82"
      },
      "Mar 2017": {
        "Promoters+": "68.08",
        "FIIs+": "22.12",
        "DIIs+": "2.67",
        "Public+": "7.12"
      },
      "Mar 2018": {
        "Promoters+": "73.07",
        "FIIs+": "11.28",
        "DIIs+": "9.14",
        "Public+": "6.51"
      },
      "Mar 2019": {
        "Promoters+": "74.97",
        "FIIs+": "10.02",
        "DIIs+": "10.11",
        "Public+": "4.90"
      },
      "Mar 2020": {
        "Promoters+": "74.97",
        "FIIs+": "12.38",
        "DIIs+": "8.29",
        "Public+": "4.35"
      },
      "Mar 2021": {
        "Promoters+": "74.97",
        "FIIs+": "11.52",
        "DIIs+": "7.08",
        "Public+": "6.43"
      },
      "Mar 2022": {
        "Promoters+": "74.97",
        "FIIs+": "11.31",
        "DIIs+": "5.56",
        "Public+": "8.15"
      }
    }
  },
  {
    "timestamp": "2025-09-25 00:45:28",
    "scan_id": "20250925_003043",
    "ticker": "ADANIPOWER",
    "quarterly_results": {
      "Sales+": {
        "Jun 2022": "13,723",
        "Sep 2022": "7,044",
        "Dec 2022": "7,764",
        "Mar 2023": "10,242",
        "Jun 2023": "11,006",
        "Sep 2023": "12,991",
        "Dec 2023": "12,991",
        "Mar 2024": "13,364",
        "Jun 2024": "14,956",
        "Sep 2024": "13,339",
        "Dec 2024": "13,671",
        "Mar 2025": "14,237",
        "Jun 2025": "14,109"
      },
      "Expenses+": {
        "Jun 2022": "8,003",
        "Sep 2022": "6,096",
        "Dec 2022": "6,295",
        "Mar 2023": "8,335",
        "Jun 2023": "7,491",
        "Sep 2023": "7,819",
        "Dec 2023": "8,346",
        "Mar 2024": "8,514",
        "Jun 2024": "8,761",
        "Sep 2024": "8,063",
        "Dec 2024": "8,648",
        "Mar 2025": "9,425",
        "Jun 2025": "8,424"
      },
      "Operating Profit": {
        "Jun 2022": "5,720",
        "Sep 2022": "948",
        "Dec 2022": "1,470",
        "Mar 2023": "1,907",
        "Jun 2023": "3,514",
        "Sep 2023": "5,171",
        "Dec 2023": "4,645",
        "Mar 2024": "4,850",
        "Jun 2024": "6,194",
        "Sep 2024": "5,276",
        "Dec 2024": "5,023",
        "Mar 2025": "4,813",
        "Jun 2025": "5,685"
      },
      "OPM %": {
        "Jun 2022": "42%",
        "Sep 2022": "13%",
        "Dec 2022": "19%",
        "Mar 2023": "19%",
        "Jun 2023": "32%",
        "Sep 2023": "40%",
        "Dec 2023": "36%",
        "Mar 2024": "36%",
        "Jun 2024": "41%",
        "Sep 2024": "40%",
        "Dec 2024": "37%",
        "Mar 2025": "34%",
        "Jun 2025": "40%"
      },
      "Other Income+": {
        "Jun 2022": "1,786",
        "Sep 2022": "1,402",
        "Dec 2022": "526",
        "Mar 2023": "553",
        "Jun 2023": "7,103",
        "Sep 2023": "1,945",
        "Dec 2023": "364",
        "Mar 2024": "518",
        "Jun 2024": "518",
        "Sep 2024": "724",
        "Dec 2024": "1,162",
        "Mar 2025": "298",
        "Jun 2025": "465"
      },
      "Interest": {
        "Jun 2022": "823",
        "Sep 2022": "818",
        "Dec 2022": "946",
        "Mar 2023": "746",
        "Jun 2023": "883",
        "Sep 2023": "888",
        "Dec 2023": "797",
        "Mar 2024": "820",
        "Jun 2024": "811",
        "Sep 2024": "807",
        "Dec 2024": "957",
        "Mar 2025": "765",
        "Jun 2025": "857"
      },
      "Depreciation": {
        "Jun 2022": "816",
        "Sep 2022": "833",
        "Dec 2022": "838",
        "Mar 2023": "817",
        "Jun 2023": "935",
        "Sep 2023": "1,004",
        "Dec 2023": "1,002",
        "Mar 2024": "990",
        "Jun 2024": "996",
        "Sep 2024": "1,059",
        "Dec 2024": "1,170",
        "Mar 2025": "1,085",
        "Jun 2025": "1,089"
      },
      "Profit before tax": {
        "Jun 2022": "5,866",
        "Sep 2022": "699",
        "Dec 2022": "212",
        "Mar 2023": "898",
        "Jun 2023": "8,800",
        "Sep 2023": "5,224",
        "Dec 2023": "3,210",
        "Mar 2024": "3,558",
        "Jun 2024": "4,906",
        "Sep 2024": "4,134",
        "Dec 2024": "4,059",
        "Mar 2025": "3,261",
        "Jun 2025": "4,204"
      },
      "Tax %": {
        "Jun 2022": "19%",
        "Sep 2022": "0%",
        "Dec 2022": "96%",
        "Mar 2023": "-484%",
        "Jun 2023": "0%",
        "Sep 2023": "-26%",
        "Dec 2023": "15%",
        "Mar 2024": "23%",
        "Jun 2024": "20%",
        "Sep 2024": "20%",
        "Dec 2024": "28%",
        "Mar 2025": "20%",
        "Jun 2025": "21%"
      },
      "Net Profit+": {
        "Jun 2022": "4,780",
        "Sep 2022": "696",
        "Dec 2022": "9",
        "Mar 2023": "5,242",
        "Jun 2023": "8,759",
        "Sep 2023": "6,594",
        "Dec 2023": "2,738",
        "Mar 2024": "2,737",
        "Jun 2024": "3,913",
        "Sep 2024": "3,298",
        "Dec 2024": "2,940",
        "Mar 2025": "2,599",
        "Jun 2025": "3,305"
      },
      "EPS in Rs": {
        "Jun 2022": "2.48",
        "Sep 2022": "0.36",
        "Dec 2022": "0.00",
        "Mar 2023": "2.72",
        "Jun 2023": "4.54",
        "Sep 2023": "3.42",
        "Dec 2023": "1.42",
        "Mar 2024": "1.42",
        "Jun 2024": "2.03",
        "Sep 2024": "1.73",
        "Dec 2024": "1.59",
        "Mar 2025": "1.37",
        "Jun 2025": "1.76"
      },
      "Raw PDF": {
        "Jun 2022": "",
        "Sep 2022": "",
        "Dec 2022": "",
        "Mar 2023": "",
        "Jun 2023": "",
        "Sep 2023": "",
        "Dec 2023": "",
        "Mar 2024": "",
        "Jun 2024": "",
        "Sep 2024": "",
        "Dec 2024": "",
        "Mar 2025": "",
        "Jun 2025": ""
      }
    },
    "balance_sheet": {
      "Equity Capital": {
        "Mar 2014": "2,872",
        "Mar 2015": "2,872",
        "Mar 2016": "3,334",
        "Mar 2017": "3,857",
        "Mar 2018": "3,857",
        "Mar 2019": "3,857",
        "Mar 2020": "3,857",
        "Mar 2021": "3,857",
        "Mar 2022": "3,857",
        "Mar 2023": "3,857",
        "Mar 2024": "3,857",
        "Mar 2025": "3,857"
      },
      "Reserves": {
        "Mar 2014": "3,671",
        "Mar 2015": "2,853",
        "Mar 2016": "4,134",
        "Mar 2017": "-857",
        "Mar 2018": "-2,968",
        "Mar 2019": "3,855",
        "Mar 2020": "2,624",
        "Mar 2021": "9,256",
        "Mar 2022": "14,600",
        "Mar 2023": "26,019",
        "Mar 2024": "39,042",
        "Mar 2025": "52,490"
      },
      "Borrowings+": {
        "Mar 2014": "44,150",
        "Mar 2015": "44,742",
        "Mar 2016": "52,729",
        "Mar 2017": "52,484",
        "Mar 2018": "52,835",
        "Mar 2019": "46,980",
        "Mar 2020": "55,199",
        "Mar 2021": "52,519",
        "Mar 2022": "49,145",
        "Mar 2023": "42,350",
        "Mar 2024": "34,862",
        "Mar 2025": "39,495"
      },
      "Other Liabilities+": {
        "Mar 2014": "8,045",
        "Mar 2015": "8,008",
        "Mar 2016": "15,597",
        "Mar 2017": "16,027",
        "Mar 2018": "15,804",
        "Mar 2019": "13,293",
        "Mar 2020": "13,346",
        "Mar 2021": "13,175",
        "Mar 2022": "14,379",
        "Mar 2023": "13,596",
        "Mar 2024": "14,248",
        "Mar 2025": "17,076"
      },
      "Total Liabilities": {
        "Mar 2014": "58,739",
        "Mar 2015": "58,474",
        "Mar 2016": "75,794",
        "Mar 2017": "71,511",
        "Mar 2018": "69,528",
        "Mar 2019": "67,985",
        "Mar 2020": "75,025",
        "Mar 2021": "78,806",
        "Mar 2022": "81,981",
        "Mar 2023": "85,821",
        "Mar 2024": "92,009",
        "Mar 2025": "112,918"
      },
      "Fixed Assets+": {
        "Mar 2014": "46,365",
        "Mar 2015": "45,080",
        "Mar 2016": "56,941",
        "Mar 2017": "54,391",
        "Mar 2018": "52,137",
        "Mar 2019": "50,419",
        "Mar 2020": "55,846",
        "Mar 2021": "52,851",
        "Mar 2022": "53,274",
        "Mar 2023": "51,451",
        "Mar 2024": "63,016",
        "Mar 2025": "69,297"
      },
      "CWIP": {
        "Mar 2014": "3,660",
        "Mar 2015": "191",
        "Mar 2016": "88",
        "Mar 2017": "125",
        "Mar 2018": "120",
        "Mar 2019": "350",
        "Mar 2020": "2,347",
        "Mar 2021": "6,439",
        "Mar 2022": "10,270",
        "Mar 2023": "12,880",
        "Mar 2024": "925",
        "Mar 2025": "12,104"
      },
      "Investments": {
        "Mar 2014": "115",
        "Mar 2015": "357",
        "Mar 2016": "0",
        "Mar 2017": "164",
        "Mar 2018": "0",
        "Mar 2019": "3",
        "Mar 2020": "3",
        "Mar 2021": "20",
        "Mar 2022": "183",
        "Mar 2023": "654",
        "Mar 2024": "374",
        "Mar 2025": "1,097"
      },
      "Other Assets+": {
        "Mar 2014": "8,599",
        "Mar 2015": "12,846",
        "Mar 2016": "18,765",
        "Mar 2017": "16,831",
        "Mar 2018": "17,271",
        "Mar 2019": "17,213",
        "Mar 2020": "16,830",
        "Mar 2021": "19,495",
        "Mar 2022": "18,254",
        "Mar 2023": "20,836",
        "Mar 2024": "27,694",
        "Mar 2025": "30,418"
      },
      "Total Assets": {
        "Mar 2014": "58,739",
        "Mar 2015": "58,474",
        "Mar 2016": "75,794",
        "Mar 2017": "71,511",
        "Mar 2018": "69,528",
        "Mar 2019": "67,985",
        "Mar 2020": "75,025",
        "Mar 2021": "78,806",
        "Mar 2022": "81,981",
        "Mar 2023": "85,821",
        "Mar 2024": "92,009",
        "Mar 2025": "112,918"
      }
    },
    "cash_flow": {
      "Cash from Operating Activity+": {
        "Mar 2014": "3,238",
        "Mar 2015": "5,824",
        "Mar 2016": "5,257",
        "Mar 2017": "4,725",
        "Mar 2018": "5,101",
        "Mar 2019": "5,610",
        "Mar 2020": "5,598",
        "Mar 2021": "7,014",
        "Mar 2022": "10,233",
        "Mar 2023": "8,431",
        "Mar 2024": "14,170",
        "Mar 2025": "21,501"
      },
      "Cash from Investing Activity+": {
        "Mar 2014": "-4,700",
        "Mar 2015": "-4,737",
        "Mar 2016": "-2,692",
        "Mar 2017": "-1,212",
        "Mar 2018": "-520",
        "Mar 2019": "-984",
        "Mar 2020": "-2,304",
        "Mar 2021": "-2,188",
        "Mar 2022": "774",
        "Mar 2023": "1,545",
        "Mar 2024": "3,481",
        "Mar 2025": "-17,142"
      },
      "Cash from Financing Activity+": {
        "Mar 2014": "1,631",
        "Mar 2015": "-1,144",
        "Mar 2016": "-2,713",
        "Mar 2017": "-3,539",
        "Mar 2018": "-4,600",
        "Mar 2019": "-4,663",
        "Mar 2020": "-2,377",
        "Mar 2021": "-5,655",
        "Mar 2022": "-10,338",
        "Mar 2023": "-10,408",
        "Mar 2024": "-16,864",
        "Mar 2025": "-5,175"
      },
      "Net Cash Flow": {
        "Mar 2014": "169",
        "Mar 2015": "-58",
        "Mar 2016": "-148",
        "Mar 2017": "-26",
        "Mar 2018": "-19",
        "Mar 2019": "-37",
        "Mar 2020": "917",
        "Mar 2021": "-828",
        "Mar 2022": "669",
        "Mar 2023": "-433",
        "Mar 2024": "787",
        "Mar 2025": "-816"
      }
    },
    "ratios": {
      "Debtor Days": {
        "Mar 2014": "37",
        "Mar 2015": "68",
        "Mar 2016": "179",
        "Mar 2017": "124",
        "Mar 2018": "109",
        "Mar 2019": "131",
        "Mar 2020": "115",
        "Mar 2021": "165",
        "Mar 2022": "126",
        "Mar 2023": "109",
        "Mar 2024": "85",
        "Mar 2025": "85"
      },
      "Inventory Days": {
        "Mar 2014": "",
        "Mar 2015": "",
        "Mar 2016": "",
        "Mar 2017": "",
        "Mar 2018": "",
        "Mar 2019": "",
        "Mar 2020": "",
        "Mar 2021": "",
        "Mar 2022": "",
        "Mar 2023": "",
        "Mar 2024": "",
        "Mar 2025": ""
      },
      "Days Payable": {
        "Mar 2014": "",
        "Mar 2015": "",
        "Mar 2016": "",
        "Mar 2017": "",
        "Mar 2018": "",
        "Mar 2019": "",
        "Mar 2020": "",
        "Mar 2021": "",
        "Mar 2022": "",
        "Mar 2023": "",
        "Mar 2024": "",
        "Mar 2025": ""
      },
      "Cash Conversion Cycle": {
        "Mar 2014": "37",
        "Mar 2015": "68",
        "Mar 2016": "179",
        "Mar 2017": "124",
        "Mar 2018": "109",
        "Mar 2019": "131",
        "Mar 2020": "115",
        "Mar 2021": "165",
        "Mar 2022": "126",
        "Mar 2023": "109",
        "Mar 2024": "85",
        "Mar 2025": "85"
      },
      "Working Capital Days": {
        "Mar 2014": "-289",
        "Mar 2015": "-161",
        "Mar 2016": "-154",
        "Mar 2017": "-208",
        "Mar 2018": "-269",
        "Mar 2019": "-90",
        "Mar 2020": "-77",
        "Mar 2021": "-38",
        "Mar 2022": "-46",
        "Mar 2023": "-6",
        "Mar 2024": "16",
        "Mar 2025": "18"
      },
      "ROCE %": {
        "Mar 2014": "6%",
        "Mar 2015": "7%",
        "Mar 2016": "11%",
        "Mar 2017": "6%",
        "Mar 2018": "6%",
        "Mar 2019": "9%",
        "Mar 2020": "7%",
        "Mar 2021": "12%",
        "Mar 2022": "16%",
        "Mar 2023": "16%",
        "Mar 2024": "32%",
        "Mar 2025": "23%"
      }
    },
    "shareholding_pattern": {
      "Sep 2022": {
        "Promoters+": "74.97",
        "FIIs+": "13.23",
        "DIIs+": "0.00",
        "Public+": "11.80"
      },
      "Dec 2022": {
        "Promoters+": "74.97",
        "FIIs+": "12.88",
        "DIIs+": "0.00",
        "Public+": "12.15"
      },
      "Mar 2023": {
        "Promoters+": "74.97",
        "FIIs+": "11.70",
        "DIIs+": "0.01",
        "Public+": "13.32"
      },
      "Jun 2023": {
        "Promoters+": "74.97",
        "FIIs+": "11.95",
        "DIIs+": "0.04",
        "Public+": "13.04"
      },
      "Sep 2023": {
        "Promoters+": "70.02",
        "FIIs+": "17.51",
        "DIIs+": "0.76",
        "Public+": "11.72"
      },
      "Dec 2023": {
        "Promoters+": "71.75",
        "FIIs+": "15.86",
        "DIIs+": "1.18",
        "Public+": "11.20"
      },
      "Mar 2024": {
        "Promoters+": "71.75",
        "FIIs+": "15.91",
        "DIIs+": "1.41",
        "Public+": "10.93"
      },
      "Jun 2024": {
        "Promoters+": "72.71",
        "FIIs+": "14.73",
        "DIIs+": "1.42",
        "Public+": "11.14"
      },
      "Sep 2024": {
        "Promoters+": "74.96",
        "FIIs+": "12.66",
        "DIIs+": "1.52",
        "Public+": "10.84"
      },
      "Dec 2024": {
        "Promoters+": "74.96",
        "FIIs+": "12.34",
        "DIIs+": "1.60",
        "Public+": "11.09"
      },
      "Mar 2025": {
        "Promoters+": "74.96",
        "FIIs+": "12.36",
        "DIIs+": "1.64",
        "Public+": "11.03"
      },
      "Jun 2025": {
        "Promoters+": "74.96",
        "FIIs+": "12.46",
        "DIIs+": "1.76",
        "Public+": "10.82"
      },
      "Mar 2017": {
        "Promoters+": "68.08",
        "FIIs+": "22.12",
        "DIIs+": "2.67",
        "Public+": "7.12"
      },
      "Mar 2018": {
        "Promoters+": "73.07",
        "FIIs+": "11.28",
        "DIIs+": "9.14",
        "Public+": "6.51"
      },
      "Mar 2019": {
        "Promoters+": "74.97",
        "FIIs+": "10.02",
        "DIIs+": "10.11",
        "Public+": "4.90"
      },
      "Mar 2020": {
        "Promoters+": "74.97",
        "FIIs+": "12.38",
        "DIIs+": "8.29",
        "Public+": "4.35"
      },
      "Mar 2021": {
        "Promoters+": "74.97",
        "FIIs+": "11.52",
        "DIIs+": "7.08",
        "Public+": "6.43"
      },
      "Mar 2022": {
        "Promoters+": "74.97",
        "FIIs+": "11.31",
        "DIIs+": "5.56",
        "Public+": "8.15"
      }
    }
  }
]